MANIFEST.in
README.rst
VERSION
requirements.txt
setup.cfg
setup.py
chrome_edit_server.egg-info/PKG-INFO
chrome_edit_server.egg-info/SOURCES.txt
chrome_edit_server.egg-info/dependency_links.txt
chrome_edit_server.egg-info/entry_points.txt
chrome_edit_server.egg-info/requires.txt
chrome_edit_server.egg-info/top_level.txt
edit_server/__init__.py
edit_server/cmdline.py
edit_server/editor.py
edit_server/filters.py
edit_server/server.py
edit_server/settings.py
edit_server/util.py
tests/__init__.py
tests/test_interaction.py