Metadata-Version: 1.0
Name: chrome-edit-server
Version: 0.3.4
Summary: An edit server compatible with TextAid and "Edit with Emacs" chrome extensions"
Home-page: https://github.com/coddingtonbear/chrome-edit-server
Author: Tim Cuthbertson, Adam Coddington
Author-email: me@adamcoddington.net
License: UNKNOWN
Platform: UNKNOWN
